{"avatars": {"Lancet2": "char_285_medic2", "Castle3": "char_286_cast3", "THRMEX": "char_376_therex", "正义骑士号": "char_4000_jnight", "夜刀": "char_502_nblade", "黑角": "char_500_noirc", "巡林者": "char_503_rang", "杜林": "char_501_durin", "12F": "char_009_12fce", "芬": "char_123_fang", "香草": "char_240_wyvern", "预备干员近战": "char_504_rguard", "翎羽": "char_192_falco", "玫兰莎": "char_208_melan", "泡普卡": "char_281_popka", "卡缇": "char_209_ardign", "米格鲁": "char_122_beagle", "斑点": "char_284_spot", "克洛丝": "char_124_kroos", "安德切尔": "char_211_adnach", "预备干员狙击": "char_507_rsnipe", "炎熔": "char_121_lava", "芙蓉": "char_120_hibisc", "安赛尔": "char_212_ansel", "预备干员后勤": "char_506_rmedic", "史都华德": "char_210_stward", "预备干员术师": "char_505_rcast", "梓兰": "char_278_orchid", "夜烟": "char_141_nights", "远山": "char_109_fmout", "格雷伊": "char_253_greyy", "卡达": "char_328_cammou", "深靛": "char_469_indigo", "布丁": "char_4004_pudd", "杰西卡": "char_235_jesica", "流星": "char_126_shotst", "红云": "char_190_clour", "梅": "char_133_mm", "白雪": "char_118_yuki", "松果": "char_440_pinecn", "安比尔": "char_302_glaze", "酸糖": "char_366_acdrop", "讯使": "char_198_blackd", "清道夫": "char_149_scave", "红豆": "char_290_vigna", "桃金娘": "char_151_myrtle", "豆苗": "char_452_bstalk", "杜宾": "char_130_doberm", "缠丸": "char_289_gyuki", "断罪者": "char_159_peacok", "霜叶": "char_193_frostl", "艾丝黛尔": "char_127_estell", "慕斯": "char_185_frncat", "刻刀": "char_301_cutter", "宴": "char_337_utage", "芳汀": "char_271_spikes", "砾": "char_237_gravel", "孑": "char_272_strong", "暗索": "char_236_rope", "末药": "char_117_myrrh", "嘉维尔": "char_187_ccheal", "苏苏洛": "char_298_susuro", "调香师": "char_181_flower", "清流": "char_385_finlpp", "褐果": "char_4041_chnut", "角峰": "char_199_yak", "蛇屠箱": "char_150_snakek", "泡泡": "char_381_bubble", "古米": "char_196_sunbr", "坚雷": "char_260_durnar", "深海色": "char_110_deepcl", "地灵": "char_183_skgoat", "波登可": "char_258_podego", "罗比菈塔": "char_484_robrta", "伊桑": "char_355_ethan", "阿消": "char_277_sqrrel", "白面鸮": "char_128_plosis", "微风": "char_275_breeze", "凛冬": "char_115_headbr", "德克萨斯": "char_102_texas", "贾维": "char_349_chiave", "苇草": "char_261_sddrag", "野鬃": "char_496_wildmn", "极境": "char_401_elysm", "夜半": "char_476_blkngt", "诗怀雅": "char_308_swire", "鞭刃": "char_265_sophia", "芙兰卡": "char_106_franka", "炎客": "char_131_flameb", "Sharp": "char_508_aguard", "因陀罗": "char_155_tiger", "燧石": "char_415_flint", "拉普兰德": "char_140_whitew", "断崖": "char_294_ayer", "柏喙": "char_252_bibeak", "战车": "char_459_tachak", "幽灵鲨": "char_143_ghost", "布洛卡": "char_356_broca", "星极": "char_274_astesi", "铸铁": "char_333_sidero", "赤冬": "char_475_akafyu", "羽毛笔": "char_421_crow", "龙舌兰": "char_486_takila", "蓝毒": "char_129_bluep", "白金": "char_204_platnm", "灰喉": "char_367_swllow", "Stormeye": "char_511_asnipe", "四月": "char_365_aprl", "寒芒克洛丝": "char_1021_kroos2", "陨星": "char_219_meteo", "慑砂": "char_379_sesa", "送葬人": "char_279_excu", "奥斯塔": "char_346_aosta", "阿米娅": "char_002_amiya", "苦艾": "char_405_absin", "特米米": "char_411_tomimi", "天火": "char_166_skfire", "Pith": "char_509_acast", "惊蛰": "char_306_leizi", "蜜蜡": "char_344_beewax", "莱恩哈特": "char_373_lionhd", "薄绿": "char_388_mint", "爱丽丝": "char_338_iris", "炎狱炎熔": "char_1011_lava2", "蚀清": "char_489_serum", "耶拉": "char_4013_kjera", "洛洛": "char_4040_rockr", "梅尔": "char_242_otter", "稀音": "char_336_folivo", "赫默": "char_108_silent", "华法琳": "char_171_bldsk", "亚叶": "char_345_folnic", "Touch": "char_510_amedic", "锡兰": "char_348_ceylon", "絮雨": "char_436_whispr", "图耶": "char_402_tuye", "桑葚": "char_473_mberry", "蜜莓": "char_449_glider", "濯尘芙蓉": "char_1024_hbisc2", "临光": "char_148_nearl", "吽": "char_226_hmau", "红": "char_144_red", "槐琥": "char_243_waaifu", "卡夫卡": "char_214_kafka", "乌有": "char_455_nothin", "雷蛇": "char_107_liskam", "可颂": "char_201_moeshd", "拜松": "char_325_bison", "火神": "char_163_hpsts", "石棉": "char_378_asbest", "暮落": "char_4025_aprot2", "车尔尼": "char_4047_pianst", "闪击": "char_457_blitz", "暴雨": "char_304_zebra", "灰毫": "char_431_ashlok", "极光": "char_422_aurora", "普罗旺斯": "char_145_prove", "守林人": "char_158_milu", "安哲拉": "char_218_cuttle", "熔泉": "char_363_toddi", "埃拉托": "char_4043_erato", "崖心": "char_173_slchan", "雪雉": "char_383_snsant", "初雪": "char_174_slbell", "巫恋": "char_254_vodfox", "真理": "char_195_glassb", "格劳克斯": "char_326_glacus", "掠风": "char_433_windft", "空": "char_101_sora", "海蒂": "char_4045_heidi", "月禾": "char_343_tknogi", "九色鹿": "char_4019_ncdeer", "夏栎": "char_492_quercu", "狮蝎": "char_215_mantic", "绮良": "char_478_kirara", "食铁兽": "char_241_panda", "见行者": "char_4036_forcer", "罗宾": "char_451_robin", "霜华": "char_458_rfrost", "贝娜": "char_369_bena", "风丸": "char_4016_kazema", "能天使": "char_103_angel", "空弦": "char_332_archet", "灰烬": "char_456_ash", "黑": "char_340_shwaz", "远牙": "char_430_fartth", "W": "char_113_cqbw", "菲亚梅塔": "char_300_phenxi", "早露": "char_197_poca", "迷迭香": "char_391_rosmon", "假日威龙陈": "char_1013_chen2", "推进之王": "char_112_siege", "风笛": "char_222_bpipe", "嵯峨": "char_362_saga", "琴柳": "char_479_sleach", "焰尾": "char_420_flamtl", "伊芙利特": "char_134_ifrit", "莫斯提马": "char_213_mostma", "艾雅法拉": "char_180_amgoat", "刻俄柏": "char_2013_cerber", "夕": "char_2015_dusk", "异客": "char_472_pasngr", "卡涅利安": "char_426_billro", "澄闪": "char_377_gdglow", "黑键": "char_4046_ebnhlz", "灵知": "char_206_gnosis", "安洁莉娜": "char_291_aglina", "铃兰": "char_358_lisa", "麦哲伦": "char_248_mgllan", "浊心斯卡蒂": "char_1012_skadi2", "令": "char_2023_ling", "傀影": "char_250_phatom", "老鲤": "char_322_lmlee", "温蒂": "char_400_weedy", "阿": "char_225_haak", "歌蕾蒂娅": "char_474_glady", "水月": "char_437_mizuki", "归溟幽灵鲨": "char_1023_ghost2", "闪灵": "char_147_shining", "夜莺": "char_179_cgbird", "凯尔希": "char_003_kalts", "流明": "char_4042_lumen", "星熊": "char_136_hsguma", "塞雷娅": "char_202_demkni", "瑕光": "char_423_blemsh", "年": "char_2014_nian", "泥岩": "char_311_mudrok", "森蚺": "char_416_zumama", "号角": "char_4039_horn", "山": "char_264_f12yin", "银灰": "char_172_svrash", "棘刺": "char_293_thorns", "陈": "char_010_chen", "艾丽妮": "char_4009_irene", "煌": "char_017_huang", "史尔特尔": "char_350_surtr", "赫拉格": "char_188_helage", "帕拉斯": "char_485_pallas", "耀骑士临光": "char_1014_nearl2", "暴行": "char_230_savage", "空爆": "char_282_catap", "月见夜": "char_283_midn", "猎蜂": "char_137_brownb", "杰克": "char_347_jaksel", "夜魔": "char_164_nightm", "格拉尼": "char_220_grani", "斯卡蒂": "char_263_skadi", "阿米娅近卫": "char_1001_amiya2"}, "pools": [{"id": 1, "pool_name": "常驻寻访", "pickup_6": "空弦,推进之王", "pickup_5": "守林人,贾维,蚀清", "pickup_4": "", "pickup_s": "", "limit_pool": 0}, {"id": 2, "pool_name": "联合行动", "pickup_6": "史尔特尔,傀影,黑,嵯峨", "pickup_5": "断崖,四月,燧石,陨星,蜜蜡,爱丽丝", "pickup_4": "", "pickup_s": "", "limit_pool": 2}, {"id": 3, "pool_name": "银灰色的荣耀", "pickup_6": "银灰", "pickup_5": "初雪,崖心", "pickup_4": "角峰", "pickup_s": null, "limit_pool": 0}, {"id": 4, "pool_name": "搅动潮汐之剑", "pickup_6": "斯卡蒂", "pickup_5": "夜魔,临光", "pickup_4": "猎蜂,暗索", "pickup_s": null, "limit_pool": 0}, {"id": 5, "pool_name": "鞘中赤红", "pickup_6": "陈", "pickup_5": "诗怀雅,食铁兽", "pickup_4": "格雷伊", "pickup_s": null, "limit_pool": 0}, {"id": 6, "pool_name": "龙门特别行动专员寻访", "pickup_6": "星熊", "pickup_5": "雷蛇,陨星", "pickup_4": "", "pickup_s": null, "limit_pool": 0}, {"id": 7, "pool_name": "深夏的守夜人", "pickup_6": "黑", "pickup_5": "格劳克斯,蓝毒", "pickup_4": "苏苏洛", "pickup_s": null, "limit_pool": 0}, {"id": 8, "pool_name": "久铸尘铁", "pickup_6": "赫拉格", "pickup_5": "星极,可颂", "pickup_4": "桃金娘", "pickup_s": null, "limit_pool": 0}, {"id": 9, "pool_name": "火舞之人", "pickup_6": "艾雅法拉", "pickup_5": "普罗旺斯,幽灵鲨", "pickup_4": "", "pickup_s": null, "limit_pool": 0}, {"id": 10, "pool_name": "冰封原野", "pickup_6": "麦哲伦", "pickup_5": "送葬人,赫默", "pickup_4": "红云", "pickup_s": null, "limit_pool": 0}, {"id": 11, "pool_name": "锁与匙的守卫者", "pickup_6": "莫斯提马", "pickup_5": "槐琥,守林人", "pickup_4": "梅", "pickup_s": null, "limit_pool": 0}, {"id": 12, "pool_name": "凝电之钻", "pickup_6": "能天使", "pickup_5": "布洛卡,苇草", "pickup_4": "", "pickup_s": null, "limit_pool": 0}, {"id": 13, "pool_name": "热情，膨胀，爆发", "pickup_6": "煌", "pickup_5": "灰喉,天火", "pickup_4": "安比尔", "pickup_s": null, "limit_pool": 0}, {"id": 14, "pool_name": "地生五金", "pickup_6": "年,阿", "pickup_5": "吽", "pickup_4": "", "pickup_s": null, "limit_pool": 1}, {"id": 15, "pool_name": "百种兵器", "pickup_6": "刻俄柏", "pickup_5": "拉普兰德,惊蛰", "pickup_4": "", "pickup_s": null, "limit_pool": 0}, {"id": 16, "pool_name": "草垛上的风笛声", "pickup_6": "风笛", "pickup_5": "慑砂,凛冬", "pickup_4": "宴", "pickup_s": null, "limit_pool": 0}, {"id": 17, "pool_name": "往日幻象", "pickup_6": "傀影", "pickup_5": "巫恋,白面鸮", "pickup_4": "刻刀", "pickup_s": null, "limit_pool": 0}, {"id": 18, "pool_name": "遗愿焰火", "pickup_6": "W,温蒂", "pickup_5": "极境", "pickup_4": "", "pickup_s": null, "limit_pool": 1}, {"id": 19, "pool_name": "雾漫荒林", "pickup_6": "", "pickup_5": "石棉,月禾", "pickup_4": "", "pickup_s": null, "limit_pool": 0}, {"id": 20, "pool_name": "雪落晨心", "pickup_6": "早露", "pickup_5": "莱恩哈特,真理", "pickup_4": "波登可", "pickup_s": null, "limit_pool": 0}, {"id": 21, "pool_name": "君影轻灵", "pickup_6": "铃兰", "pickup_5": "断崖,夜魔", "pickup_4": "卡达", "pickup_s": null, "limit_pool": 0}, {"id": 22, "pool_name": "流沙涡旋", "pickup_6": "", "pickup_5": "蜜蜡,贾维", "pickup_4": "", "pickup_s": null, "limit_pool": 0}, {"id": 23, "pool_name": "不羁逆流", "pickup_6": "棘刺", "pickup_5": "安哲拉,普罗旺斯", "pickup_4": "孑", "pickup_s": null, "limit_pool": 0}, {"id": 24, "pool_name": "燃钢之心，暴躁铁皮", "pickup_6": "森蚺", "pickup_5": "燧石,陨星", "pickup_4": "酸糖", "pickup_s": null, "limit_pool": 0}, {"id": 25, "pool_name": "无拘熔火", "pickup_6": "史尔特尔", "pickup_5": "四月,极境", "pickup_4": "芳汀", "pickup_s": null, "limit_pool": 0}, {"id": 26, "pool_name": "瑕光微明", "pickup_6": "瑕光", "pickup_5": "奥斯塔,白金", "pickup_4": "泡泡", "pickup_s": null, "limit_pool": 0}, {"id": 27, "pool_name": "勿忘我", "pickup_6": "迷迭香,泥岩", "pickup_5": "絮雨", "pickup_4": "杰克", "pickup_s": null, "limit_pool": 1}, {"id": 28, "pool_name": "自由的囚徒", "pickup_6": "山", "pickup_5": "卡夫卡,赫默", "pickup_4": "松果", "pickup_s": null, "limit_pool": 0}, {"id": 29, "pool_name": "麦穗与赞美诗", "pickup_6": "空弦", "pickup_5": "爱丽丝,贾维", "pickup_4": "豆苗", "pickup_s": null, "limit_pool": 0}, {"id": 30, "pool_name": "月隐晦明", "pickup_6": "夕,嵯峨", "pickup_5": "乌有", "pickup_4": "", "pickup_s": "年|5", "limit_pool": 1}, {"id": 31, "pool_name": "进攻、防守、战术交汇", "pickup_6": "灰烬", "pickup_5": "霜华,闪击", "pickup_4": "", "pickup_s": null, "limit_pool": 1}, {"id": 32, "pool_name": "沙海过客", "pickup_6": "异客", "pickup_5": "熔泉", "pickup_4": "", "pickup_s": null, "limit_pool": 0}, {"id": 33, "pool_name": "深悼", "pickup_6": "浊心斯卡蒂,凯尔希", "pickup_5": "赤冬", "pickup_4": "", "pickup_s": "W|5", "limit_pool": 1}, {"id": 34, "pool_name": "革新交响曲", "pickup_6": "卡涅利安", "pickup_5": "绮良,崖心", "pickup_4": "深靛", "pickup_s": null, "limit_pool": 0}, {"id": 35, "pool_name": "从星火中来", "pickup_6": "帕拉斯", "pickup_5": "幽灵鲨,红", "pickup_4": "", "pickup_s": null, "limit_pool": 0}, {"id": 36, "pool_name": "盛夏新星", "pickup_6": "假日威龙陈,水月", "pickup_5": "羽毛笔", "pickup_4": "", "pickup_s": null, "limit_pool": 1}, {"id": 37, "pool_name": "小丘上的眠柳", "pickup_6": "琴柳", "pickup_5": "桑葚,雷蛇", "pickup_4": "罗比菈塔", "pickup_s": null, "limit_pool": 0}, {"id": 38, "pool_name": "漂泊于风", "pickup_6": "远牙", "pickup_5": "灰毫,狮蝎", "pickup_4": "", "pickup_s": "", "limit_pool": 0}, {"id": 39, "pool_name": "循光道途", "pickup_6": "耀骑士临光,焰尾", "pickup_5": "蚀清", "pickup_4": "", "pickup_s": "W|5,迷迭香|5", "limit_pool": 1}, {"id": 40, "pool_name": "雪融之诺", "pickup_6": "灵知", "pickup_5": "初雪,极光", "pickup_4": "", "pickup_s": "", "limit_pool": 0}, {"id": 41, "pool_name": "浊酒澄心", "pickup_6": "令,老鲤", "pickup_5": "夜半", "pickup_4": "", "pickup_s": "年|5,夕|5", "limit_pool": 1}, {"id": 42, "pool_name": "火花绽放", "pickup_6": "澄闪", "pickup_5": "夏栎,天火", "pickup_4": "", "pickup_s": "", "limit_pool": 0}, {"id": 43, "pool_name": "炽焰无霾", "pickup_6": "菲亚梅塔", "pickup_5": "风丸,送葬人", "pickup_4": "", "pickup_s": "", "limit_pool": 0}, {"id": 44, "pool_name": "奔崖怒号", "pickup_6": "号角", "pickup_5": "洛洛,华法琳", "pickup_4": "褐果", "pickup_s": "", "limit_pool": 0}, {"id": 45, "pool_name": "海蚀", "pickup_6": "艾丽妮,归溟幽灵鲨", "pickup_5": "掠风", "pickup_4": "", "pickup_s": "W|5,迷迭香|5,浊心斯卡蒂|5", "limit_pool": 1}, {"id": 46, "pool_name": "不协和音程", "pickup_6": "黑键", "pickup_5": "濯尘芙蓉,蓝毒", "pickup_4": "", "pickup_s": null, "limit_pool": 0}]}